<effectgroup description="缩放、推拉镜头效果" id="zoom_6534" parentIn="0">
 <description>缩放、推拉镜头效果</description>
 <effect id="qtblend">
  <property name="rotation">0=0;106=0</property>
  <property name="rect">0=-77 -137 1234 2195 1.000000;106=36 63 1008 1793 1.000000</property>
  <property name="rotate_center">1</property>
  <property name="distort">0</property>
  <property name="compositing">0</property>
 </effect>
 <effect id="frei0r.lenscorrection">
  <property name="correctionnearcenter">0=0.5;106=0.13169313260059856</property>
  <property name="brightness">0=0;106=0.2010799152163586</property>
  <property name="correctionnearedges">0=0.5;106=0.13169313260059856</property>
  <property name="ycenter">0=0.5;106=0.5</property>
  <property name="xcenter">0=0.5;106=0.5</property>
 </effect>
</effectgroup>